reifier/__init__.py
reifier/compile/__init__.py
reifier/compile/blocks.py
reifier/compile/draw_blocks.py
reifier/compile/levels.py
reifier/compile/metadata_adder.py
reifier/compile/monitor.py
reifier/compile/tree.py
reifier/data/__init__.py
reifier/data/base.py
reifier/data/conjunction.py
reifier/data/parity.py
reifier/data/sandbag.py
reifier/examples/__init__.py
reifier/examples/backdoors.py
reifier/examples/compilation_example.py
reifier/examples/example_circuit.png
reifier/examples/flat.py
reifier/examples/keccak.py
reifier/examples/other/keccak_fused.py
reifier/examples/other/sha2.py
reifier/examples/other/sha3.py
reifier/examples/other/simple_example.py
reifier/examples/sandbagging.py
reifier/examples/sandbagging_parity.py
reifier/neurons/__init__.py
reifier/neurons/core.py
reifier/neurons/operations.py
reifier/sparse/__init__.py
reifier/sparse/compile.py
reifier/sparse/sparse_graph.py
reifier/tensors/__init__.py
reifier/tensors/compilation.py
reifier/tensors/matrices.py
reifier/tensors/mlp.py
reifier/tensors/mlp_old.py
reifier/tensors/mlp_utils.py
reifier/tensors/step.py
reifier/tensors/swiglu.py
reifier/tensors/swiglu_utils.py
reifier/tensors/symmetries.py
reifier/train/__init__.py
reifier/train/logging.py
reifier/train/noiser.py
reifier/train/train.py
reifier/train/train_utils.py
reifier/utils/__init__.py
reifier/utils/format.py
reifier/utils/misc.py
reifier/visuals/distr.py
reifier/visuals/swiglu.py
reifier-0.0.3.dist-info/WHEEL
reifier-0.0.3.dist-info/METADATA
reifier-0.0.3.dist-info/RECORD
