Metadata-Version: 2.3
Name: reifier
Version: 0.0.3
Summary: Neural network compilation
Author: Andis Draguns
License: MIT
Requires-Dist: numpy>=1.26.0
Requires-Dist: torch>=2.8,<2.9 ; extra == 'cpu'
Requires-Dist: torchvision>=0.23,<0.24 ; extra == 'cpu'
Requires-Dist: torch>=2.8,<2.9 ; extra == 'cu128'
Requires-Dist: torchvision>=0.23,<0.24 ; extra == 'cu128'
Requires-Python: >=3.12
Provides-Extra: cpu
Provides-Extra: cu128
